{
  "collectionName": "components_blocks_right_therapist",
  "info": { "displayName": "Right Therapist" },
  "options": {},
  "attributes": {
    "title": { "type": "string", "required": true },
    "description": { "type": "text", "required": true },
    "subtitle": { "type": "string", "required": true },
    "footerText": { "type": "string", "required": true },
    "features": {
      "type": "component",
      "repeatable": true,
      "component": "pagesections.feature",
      "required": true
    },
    "cta": {
      "type": "component",
      "repeatable": true,
      "component": "pagesections.cta",
      "required": true
    }
  }
}
